{
  "Users": [
    {
      "id": "12",
      "email": "mgemal@gmail.com",
      "firstName": "Mohammed",
      "lastName": "Mohammed",
      "password": "Mohammed123",
      "gender": "male"
    },
    {
      "id": "2",
      "email": "m@g.com",
      "firstName": "Mohammed",
      "lastName": "gemal",
      "password": "Mohammed123",
      "gender": "male"
    },
    {
      "id": "6",
      "email": "mgemal376@gmail.com",
      "firstName": "Hame",
      "lastName": "Esrom",
      "password": "Mohammed123",
      "gender": "Male"
    },
    {
      "id": "30",
      "email": "miki@gmail.com",
      "firstName": "Naodd",
      "lastName": "Mikii",
      "password": "test123",
      "gender": "Male"
    },
    {
      "id": "101",
      "email": "mgemal375@gmail.com",
      "firstName": "Naod",
      "lastName": "Gemal",
      "password": "test123",
      "gender": "Male"
    },
    {
      "id": "202",
      "email": "help@gmail.com",
      "firstName": "Please",
      "lastName": "Work",
      "password": "Help123",
      "gender": "male"
    },
    {
      "id": "900",
      "email": "miki@gmail.com",
      "firstName": "Miki",
      "lastName": "Miki",
      "password": "123#Miki",
      "gender": "Female"
    },
    {
      "id": "1",
      "email": "alex@gmail.com",
      "firstName": "Alex",
      "lastName": "Richard",
      "password": "Alex123#",
      "gender": "Male"
    }
  ],
  "answers": [
    {
      "id": 1,
      "answer": "Apple",
      "isCorrect": false
    },
    {
      "id": 2,
      "answer": "July 2017",
      "isCorrect": false
    },
    {
      "id": 3,
      "answer": "Int",
      "isCorrect": false
    },
    {
      "id": 4,
      "answer": "Count",
      "isCorrect": false
    }
  ]
}